README.md
setup.py
src/xllib/__init__.py
src/xllib/utils.py
src/xllib/xlio.py
src/xllib/xlmerge.py
src/xllib/xlstyle.py
src/xllib.egg-info/PKG-INFO
src/xllib.egg-info/SOURCES.txt
src/xllib.egg-info/dependency_links.txt
src/xllib.egg-info/entry_points.txt
src/xllib.egg-info/requires.txt
src/xllib.egg-info/top_level.txt
test/test.py